CHANGELOG.txt
LICENSE.txt
MANIFEST.in
README.txt
setup.py
pivumeter/__init__.py
pivumeter.egg-info/PKG-INFO
pivumeter.egg-info/SOURCES.txt
pivumeter.egg-info/dependency_links.txt
pivumeter.egg-info/top_level.txt